{
  "project_info": {
    "project_number": "992021479808",
    "firebase_url": "https://pinnote-4800d.firebaseio.com",
    "project_id": "pinnote-4800d",
    "storage_bucket": "pinnote-4800d.appspot.com"
  },
  "client": [
    {
      "client_info": {
        "mobilesdk_app_id": "1:992021479808:android:65d5dbb91a505c157d8165",
        "android_client_info": {
          "package_name": "com.example.pin_note1"
        }
      },
      "oauth_client": [
        {
          "client_id": "992021479808-gk1tgisj28t83mc34907sqofqbsjis1h.apps.googleusercontent.com",
          "client_type": 3
        }
      ],
      "api_key": [
        {
          "current_key": "AIzaSyBjjgDwkpR41ADkKiD6ZvvPrrSbu1WHNHM"
        }
      ],
      "services": {
        "appinvite_service": {
          "other_platform_oauth_client": [
            {
              "client_id": "992021479808-gk1tgisj28t83mc34907sqofqbsjis1h.apps.googleusercontent.com",
              "client_type": 3
            }
          ]
        }
      }
    }
  ],
  "configuration_version": "1"
}